traits/__init__.py
traits/__init__.pyi
traits/api.py
traits/api.pyi
traits/base_trait_handler.py
traits/base_trait_handler.pyi
traits/constants.py
traits/constants.pyi
traits/ctrait.py
traits/ctrait.pyi
traits/ctraits.cpython-313-x86_64-linux-musl.so
traits/ctraits.pyi
traits/editor_factories.py
traits/editor_factories.pyi
traits/has_traits.py
traits/has_traits.pyi
traits/interface_checker.py
traits/py.typed
traits/trait_base.py
traits/trait_converters.py
traits/trait_dict_object.py
traits/trait_errors.py
traits/trait_factory.py
traits/trait_handler.py
traits/trait_handler.pyi
traits/trait_handlers.py
traits/trait_handlers.pyi
traits/trait_list_object.py
traits/trait_notifiers.py
traits/trait_numeric.py
traits/trait_numeric.pyi
traits/trait_set_object.py
traits/trait_type.py
traits/trait_type.pyi
traits/trait_types.py
traits/trait_types.pyi
traits/traits.py
traits/traits.pyi
traits/traits_listener.py
traits/traits_notifiers.pyi
traits/version.py
traits/adaptation/__init__.py
traits/adaptation/adaptation_error.py
traits/adaptation/adaptation_manager.py
traits/adaptation/adaptation_offer.py
traits/adaptation/adapter.py
traits/adaptation/api.py
traits/adaptation/tests/__init__.py
traits/adaptation/tests/abc_examples.py
traits/adaptation/tests/benchmark.py
traits/adaptation/tests/interface_examples.py
traits/adaptation/tests/lazy_examples.py
traits/adaptation/tests/test_adaptation_manager.py
traits/adaptation/tests/test_adaptation_offer.py
traits/adaptation/tests/test_adapter.py
traits/adaptation/tests/test_global_adaptation_manager.py
traits/etsconfig/__init__.py
traits/etsconfig/api.py
traits/etsconfig/etsconfig.py
traits/etsconfig/tests/__init__.py
traits/etsconfig/tests/test_etsconfig.py
traits/examples/__init__.py
traits/examples/_etsdemo_info.py
traits/examples/introduction/0_introduction.py
traits/examples/introduction/1_validation.py
traits/examples/introduction/2_initialization.py
traits-7.1.0.dist-info/METADATA
traits-7.1.0.dist-info/WHEEL
traits-7.1.0.dist-info/entry_points.txt
traits-7.1.0.dist-info/top_level.txt
traits-7.1.0.dist-info/RECORD
traits-7.1.0.dist-info/licenses/LICENSE-CC-BY-3.0.txt
traits-7.1.0.dist-info/licenses/LICENSE.txt
