Metadata-Version: 2.1
Name: traits
Version: 7.1.0
Summary: Observable typed attributes for Python classes
Home-page: http://docs.enthought.com/traits
Download-URL: https://pypi.python.org/pypi/traits
Author: Enthought
Author-email: info@enthought.com
License: BSD
Project-URL: Issue Tracker, https://github.com/enthought/traits/issues
Project-URL: Documentation, https://docs.enthought.com/traits
Project-URL: Source Code, https://github.com/enthought/traits
Classifier: Development Status :: 5 - Production/Stable
Classifier: Intended Audience :: Developers
Classifier: Intended Audience :: Science/Research
Classifier: License :: OSI Approved :: BSD License
Classifier: Operating System :: MacOS :: MacOS X
Classifier: Operating System :: Microsoft :: Windows
Classifier: Operating System :: POSIX :: Linux
Classifier: Programming Language :: Python
Classifier: Programming Language :: Python :: 3
Classifier: Programming Language :: Python :: Implementation :: CPython
Classifier: Topic :: Scientific/Engineering
Classifier: Topic :: Software Development
Classifier: Topic :: Software Development :: Libraries
Classifier: Topic :: Software Development :: User Interfaces
Classifier: Typing :: Typed
Requires-Python: >=3.8
License-File: LICENSE-CC-BY-3.0.txt
License-File: LICENSE.txt
Provides-Extra: docs
Requires-Dist: enthought-sphinx-theme; extra == "docs"
Requires-Dist: Sphinx>=2.1.0; extra == "docs"
Requires-Dist: sphinx-copybutton; extra == "docs"
Provides-Extra: examples
Requires-Dist: numpy; extra == "examples"
Requires-Dist: pillow; extra == "examples"
Provides-Extra: test
Requires-Dist: defusedxml; extra == "test"
Requires-Dist: flake8; extra == "test"
Requires-Dist: flake8-ets; extra == "test"
Requires-Dist: mypy; extra == "test"
Requires-Dist: numpy; extra == "test"
Requires-Dist: pyface; extra == "test"
Requires-Dist: setuptools; extra == "test"
Requires-Dist: Sphinx>=2.1.0; extra == "test"
Requires-Dist: traitsui; extra == "test"
